findmyorder/__init__.py
findmyorder/config.py
findmyorder/main.py
findmyorder/handler/__init__.py
findmyorder/handler/_client.py
findmyorder/handler/basic.py
findmyorder/handler/standard.py
findmyorder-4.0.1.dist-info/licenses/LICENSE
findmyorder-4.0.1.dist-info/METADATA
findmyorder-4.0.1.dist-info/WHEEL
findmyorder-4.0.1.dist-info/top_level.txt
findmyorder-4.0.1.dist-info/RECORD
