Metadata-Version: 2.4
Name: findmyorder
Version: 4.0.1
Summary: A python package to identify and parse order for trade execution.
Author-email: mraniki <8766259+mraniki@users.noreply.github.com>
License-Expression: MIT
Project-URL: Homepage, https://github.com/mraniki/findmyorder
Project-URL: Changelog, https://github.com/mraniki/findmyorder/blob/dev/CHANGELOG.rst
Project-URL: Support, https://github.com/mraniki/findmyorder/discussions
Project-URL: Issues, https://github.com/mraniki/findmyorder/issues
Keywords: trading,order,trade,buy,sell
Classifier: Programming Language :: Python :: 3
Classifier: Programming Language :: Python :: 3.10
Classifier: Programming Language :: Python :: 3.11
Classifier: Programming Language :: Python :: 3.12
Requires-Python: >=3.10
License-File: LICENSE
Requires-Dist: dynaconf>=3.2.0
Requires-Dist: loguru>=0.6.0
Requires-Dist: pyparsing>=3.0.9
Provides-Extra: dev
Requires-Dist: python-semantic-release>=8.0.8; extra == "dev"
Requires-Dist: ruff~=0.7; extra == "dev"
Requires-Dist: pre-commit~=3.3; extra == "dev"
Provides-Extra: test
Requires-Dist: pytest~=8.0; extra == "test"
Requires-Dist: pytest-cov~=5.0; extra == "test"
Requires-Dist: pytest-asyncio~=0.24; extra == "test"
Requires-Dist: pytest-mock~=3.11; extra == "test"
Requires-Dist: pytest-loguru~=0.4; extra == "test"
Provides-Extra: docs
Requires-Dist: sphinx==7.4.7; extra == "docs"
Requires-Dist: pydata-sphinx-theme~=0.14; extra == "docs"
Requires-Dist: sphinx-hoverxref~=1.3; extra == "docs"
Requires-Dist: sphinx_copybutton==0.5.2; extra == "docs"
Requires-Dist: myst_parser~=4.0; extra == "docs"
Requires-Dist: sphinx_design~=0.6; extra == "docs"
Dynamic: license-file
